edgar/archives.py
edgar/client.py
edgar/companies.py
edgar/current_events.py
edgar/datasets.py
edgar/enums.py
edgar/filings.py
edgar/issuers.py
edgar/mutual_funds.py
edgar/ownership_filings.py
edgar/parser.py
edgar/series.py
edgar/session.py
edgar/submissions.py
edgar/utilis.py
edgar/variable_insurance_products.py
edgar/xbrl.py
edgar/parsing/__init__.py
edgar/parsing/country_code.html
edgar/parsing/dropdown_html.html
edgar/parsing/parse_country.py
edgar/parsing/state_codes.html
samples/use_api_submissions.py
samples/use_api_xbrl.py
samples/use_archive_service.py
samples/use_client.py
samples/use_company_service.py
samples/use_current_events_service.py
samples/use_dataset_service.py
samples/use_filings_service.py
samples/use_issuers_service.py
samples/use_mutual_funds_service.py
samples/use_ownership_filings_service.py
samples/use_series_service.py
samples/use_variable_insurance_products.py
tests/test_edgar_client.py
python_sec-0.1.6.dist-info/LICENSE
python_sec-0.1.6.dist-info/METADATA
python_sec-0.1.6.dist-info/WHEEL
python_sec-0.1.6.dist-info/top_level.txt
python_sec-0.1.6.dist-info/RECORD
