Metadata-Version: 2.1
Name: python-sec
Version: 0.1.6
Summary: A client library for collecting and scraping SEC filings.
Home-page: https://github.com/areed1192/python-sec
Author: Alex Reed
Author-email: coding.sigma@gmail.com
License: UNKNOWN
Keywords: finance,sec,api,web scraping,financial disclosures
Platform: UNKNOWN
Classifier: Development Status :: 3 - Alpha
Classifier: Intended Audience :: Financial and Insurance Industry
Classifier: License :: OSI Approved :: MIT License
Classifier: Natural Language :: English
Classifier: Operating System :: OS Independent
Classifier: Programming Language :: Python :: 3
Requires-Python: >=3.7
Requires-Dist: requests (==2.25.1)
Requires-Dist: urllib3 (==1.26.5)
Requires-Dist: beautifulsoup4 (==4.9.1)
